msci_esg/__init__.py
msci_esg/ratefinder.py
msci_esg_pkg/__init__.py
py_msci_esg-0.0.8.dist-info/LICENSE
py_msci_esg-0.0.8.dist-info/METADATA
py_msci_esg-0.0.8.dist-info/WHEEL
py_msci_esg-0.0.8.dist-info/top_level.txt
py_msci_esg-0.0.8.dist-info/RECORD
