Metadata-Version: 2.1
Name: py-msci-esg
Version: 0.0.8
Summary: A package for scraping content from the MSCI.com ESG Ratings Corporate Search Tool
Home-page: https://github.com/austinjhunt/msci_esg
Author: Austin Hunt
Author-email: huntaj@g.cofc.edu
License: UNKNOWN
Project-URL: Bug Tracker, https://github.com/austinjhunt/msci_esg/issues
Platform: UNKNOWN
Classifier: Programming Language :: Python :: 3
Classifier: License :: OSI Approved :: MIT License
Classifier: Operating System :: OS Independent
Requires-Python: >=3.6
